sajjad/__init__.py
sajjad/sajjad.py
sajjad-2.1.dist-info/METADATA
sajjad-2.1.dist-info/WHEEL
sajjad-2.1.dist-info/top_level.txt
sajjad-2.1.dist-info/RECORD
