Metadata-Version: 2.1
Name: sajjad
Version: 2.1
Summary: Sajjad developer creatd this library
Author: sajjad seyedi
Author-email: sajjad.seyedi.88@gmail.com
Classifier: Development Status :: 3 - Alpha
Classifier: Intended Audience :: Developers
Classifier: License :: OSI Approved :: MIT License
Classifier: Programming Language :: Python :: 3.6
Classifier: Programming Language :: Python :: 3.7
Classifier: Programming Language :: Python :: 3.8
Requires-Dist: colorama (==0.4.6)
